simple_graph_libsql/__init__.py
simple_graph_libsql/database.py
simple_graph_libsql/sql/delete-edge.sql
simple_graph_libsql/sql/delete-node.sql
simple_graph_libsql/sql/insert-edge.sql
simple_graph_libsql/sql/insert-node.sql
simple_graph_libsql/sql/schema.sql
simple_graph_libsql/sql/search-edges-inbound.sql
simple_graph_libsql/sql/search-edges-outbound.sql
simple_graph_libsql/sql/search-edges.sql
simple_graph_libsql/sql/search-node.template
simple_graph_libsql/sql/search-where.template
simple_graph_libsql/sql/traverse.template
simple_graph_libsql/sql/update-node.sql
simple_graph_libsql/visualizers.py
simple_graph_libsql-2.1.0.dist-info/LICENSE
simple_graph_libsql-2.1.0.dist-info/METADATA
simple_graph_libsql-2.1.0.dist-info/WHEEL
simple_graph_libsql-2.1.0.dist-info/RECORD
