Metadata-Version: 2.1
Name: simple-graph-libsql
Version: 2.1.0
Summary: A simple graph database in LibSQL
License: MIT
Author: Your Name
Author-email: you@example.com
Requires-Python: >=3.8,<4.0
Classifier: License :: OSI Approved :: MIT License
Classifier: Programming Language :: Python :: 3
Classifier: Programming Language :: Python :: 3.8
Classifier: Programming Language :: Python :: 3.9
Classifier: Programming Language :: Python :: 3.10
Classifier: Programming Language :: Python :: 3.11
Classifier: Programming Language :: Python :: 3.12
Requires-Dist: graphviz (>=0.20.1,<0.21.0)
Requires-Dist: jinja2 (>=3.1.3,<4.0.0)
Requires-Dist: libsql-experimental (>=0.0.26,<0.0.27)
Requires-Dist: python-dotenv (>=1.0.1,<2.0.0)
